random_recipes/__init__.py
random_recipes/collections.py
random_recipes/files.py
random_recipes/objects.py
random_recipes-0.1.0.dist-info/LICENSE
random_recipes-0.1.0.dist-info/METADATA
random_recipes-0.1.0.dist-info/WHEEL
random_recipes-0.1.0.dist-info/RECORD
