Metadata-Version: 2.1
Name: random-recipes
Version: 0.1.0
Summary: Recipes to generate random instances of various types, beyond the scope of random.
Home-page: https://pypi.org/project/random-recipes/
License: MIT
Keywords: random
Author: Ian Pearthree
Author-email: 52967928+ipear3@users.noreply.github.com
Requires-Python: >=3.11,<4.0
Classifier: License :: OSI Approved :: MIT License
Classifier: Programming Language :: Python :: 3
Classifier: Programming Language :: Python :: 3.11
Project-URL: Repository, https://github.com/ipear3/random-recipes
